<?xml version="1.0" encoding="UTF-8"?>

<process-definition lang="Filipino" xmlns="" name="alternative learning system">

	<start-state name="start-state1">
		<transition to="special~Mga Kaalamang Maaring Alam Mo Na"></transition>
	</start-state>


	<task-node name="radioButtons~1~Alin sa mga sumusunod ang HINDI katwiran sa pag-uuri ng mga halaman? ">
		<task name="Upang maisaayos ang iba't ibang uri ng mga halaman."></task>
		<task name="Upang madaling makilala ang mga pangkat ng halaman ayon sa kanilang tiyak na mga katangian."></task>
		<task name="Upang mauri ang mga halaman sa mas maliliit na pangkat nang mas madaling makilala ang mga ito."></task>
		<task name="Upang hanapin ang kaugnayan sa pagitan ng mga halaman at mga hayop."></task>
		<transition to="end-state1" name="Any"></transition>
	</task-node>

	<task-node name="special~Mga Kaalamang Maaring Alam Mo Na">
		<transition to="special~Bago mo pag-aralan ang modyul na ito, sagutin mo muna ang mga katanungan sa ibaba upang malaman kung gaano na ang kaalaman mo." name="Any"></transition>
	</task-node>

	<task-node name="special~Bago mo pag-aralan ang modyul na ito, sagutin mo muna ang mga katanungan sa ibaba upang malaman kung gaano na ang kaalaman mo.">
		<transition to="radioButtons~1~Alin sa mga sumusunod ang HINDI katwiran sa pag-uuri ng mga halaman? " name="Any"></transition>
	</task-node>

	<end-state name="end-state1"></end-state>
</process-definition>